PyEqCloud.py
PyEqCloud-0.2.5.dist-info/LICENSE.txt
PyEqCloud-0.2.5.dist-info/METADATA
PyEqCloud-0.2.5.dist-info/WHEEL
PyEqCloud-0.2.5.dist-info/top_level.txt
PyEqCloud-0.2.5.dist-info/RECORD
