Metadata-Version: 2.1
Name: PyEqCloud
Version: 0.2.5
Summary: Gather Data via a REST-Connection from the Kontron AIS GmbH EquipmentCloud
Home-page: UNKNOWN
Author: Maik Pertermann, until March 2021 Patrick Thiem 
Author-email: maik.pertermann@kontron-ais.com, Patrick.Thiem@kontron-ais.com
License: MIT
Keywords: equipment cloud
Platform: UNKNOWN
Classifier: Development Status :: 3 - Alpha
Classifier: Intended Audience :: Developers
Classifier: Intended Audience :: Science/Research
Classifier: Programming Language :: Python :: 3.6
Classifier: Programming Language :: Python :: 3.7
Classifier: Programming Language :: Python :: 3.8
Requires-Python: >=3.6
Requires-Dist: requests (>=2.22.0)
Requires-Dist: pandas (>=0.23.4)
Requires-Dist: tqdm (>=4.39.0)
